json_analyzer-0.1.0.dist-info/licenses/LICENSE
json_explorer/__init__.py
json_explorer/__main__.py
json_explorer/analyzer.py
json_explorer/cli.py
json_explorer/filter_parser.py
json_explorer/interactive.py
json_explorer/main.py
json_explorer/search.py
json_explorer/stats.py
json_explorer/tree_view.py
json_explorer/utils.py
json_explorer/visualizer.py
tests/__init__.py
tests/test_analyzer.py
tests/test_search.py
tests/test_stats.py
tests/test_tree_view.py
tests/test_utils.py
tests/test_visualizer.py
json_analyzer-0.1.0.dist-info/METADATA
json_analyzer-0.1.0.dist-info/WHEEL
json_analyzer-0.1.0.dist-info/entry_points.txt
json_analyzer-0.1.0.dist-info/top_level.txt
json_analyzer-0.1.0.dist-info/RECORD
