Metadata-Version: 2.4
Name: json-analyzer
Version: 0.1.0
Summary: Analyze, visualize, and explore JSON data from files or URLs
Author: Muaaz Alsaied
Author-email: Muaaze Alsaied <muaaz.alsaied@gmail.com>
License: MIT License
Requires-Python: >=3.7
License-File: LICENSE
Requires-Dist: rich
Requires-Dist: requests
Requires-Dist: matplotlib
Requires-Dist: numpy
Dynamic: license-file
